[
  {
    "name": "Cosmopolitan Maracujá",
    "nameItalic": "Cosmo Maracujá",
    "perfil": "Cítrico frutado",
    "copo": "Taça Cocktail",
    "foto": "https://raw.githubusercontent.com/botecoconstantepimenta-cmyk/BotecoCP/refs/heads/main/Encarte%20Cosmopolitan%20Maracuj%C3%A1.png",
    "ingredientes": [
      { "qty": "50ml", "name": "Vodka" },
      { "qty": "15ml", "name": "Suco de Limão" },
      { "qty": "40ml", "name": "Maracujá" },
      { "qty": "25ml", "name": "Licor de Laranja" },
      { "qty": "30ml", "name": "Suco de Cranberry" }
    ],
    "preparo": [
      "Adicione gelo em uma taça.",
      "Coloque todos os ingredientes na coqueteleira.",
      "Bata bem e faça dupla coagem na taça."
    ]
  },
  {
    "name": "Lagoa Azul",
    "nameItalic": "Blue Lagoon",
    "perfil": "Doce cítrico",
    "copo": "Copo Longo",
    "foto": "https://raw.githubusercontent.com/botecoconstantepimenta-cmyk/BotecoCP/refs/heads/main/Encarte%20Lago%20Azul.png",
    "ingredientes": [
      { "qty": "50ml", "name": "Vodka ou Cachaça" },
      { "qty": "30ml", "name": "Curaçau Blue" },
      { "qty": "20ml", "name": "Suco de Limão" },
      { "qty": "Top", "name": "Refrigerante de Limão" }
    ],
    "preparo": [
      "Adicione gelo ao copo.",
      "Coloque todos os ingredientes diretamente no copo.",
      "Misture levemente."
    ]
  },
  {
    "name": "Mojito",
    "nameItalic": "Mojito",
    "perfil": "Refrescante cítrico",
    "copo": "Copo Longo",
    "foto": "https://images.unsplash.com/photo-1582578598774-a377d4b322c6?q=80&w=400",
    "ingredientes": [
      { "qty": "8 folhas", "name": "Hortelã" },
      { "qty": "30ml", "name": "Suco de Limão" },
      { "qty": "45ml", "name": "Rum Branco" },
      { "qty": "Top", "name": "Água com Gás" }
    ],
    "preparo": [
      "Passe hortelã na borda do copo.",
      "Macere levemente para liberar aroma.",
      "Adicione gelo e os demais ingredientes.",
      "Complete com água com gás."
    ]
  },
  {
    "name": "Aperol Spritz",
    "nameItalic": "Aperol",
    "perfil": "Amargo refrescante",
    "copo": "Taça Vinho",
    "foto": "https://images.unsplash.com/photo-1595977437232-9fbc1f4c8f76?q=80&w=400",
    "ingredientes": [
      { "qty": "60ml", "name": "Aperol" },
      { "qty": "20ml", "name": "Suco de Limão" },
      { "qty": "90ml", "name": "Refrigerante de Laranja" },
      { "qty": "5 dashes", "name": "Bitter" }
    ],
    "preparo": [
      "Adicione gelo ao copo.",
      "Coloque todos os ingredientes.",
      "Misture suavemente."
    ]
  },
  {
    "name": "Cuba Libre",
    "nameItalic": "Cuba",
    "perfil": "Refrescante doce",
    "copo": "Copo Longo",
    "foto": "https://images.unsplash.com/photo-1625943553852-781c6dd46faa?q=80&w=400",
    "ingredientes": [
      { "qty": "50ml", "name": "Rum" },
      { "qty": "25ml", "name": "Suco de Limão" },
      { "qty": "200ml", "name": "Coca-Cola" }
    ],
    "preparo": [
      "Adicione gelo ao copo.",
      "Coloque todos os ingredientes diretamente no copo.",
      "Misture suavemente."
    ]
  },
  {
    "name": "Margarita",
    "nameItalic": "Margarita",
    "perfil": "Cítrico forte",
    "copo": "Taça Margarita",
    "foto": "https://images.unsplash.com/photo-1556855810-ac404aa91e85?q=80&w=400",
    "ingredientes": [
      { "qty": "50ml", "name": "Tequila" },
      { "qty": "25ml", "name": "Suco de Limão" },
      { "qty": "25ml", "name": "Licor de Laranja" }
    ],
    "preparo": [
      "Passe limão na borda da taça e adicione sal.",
      "Coloque os ingredientes na coqueteleira com gelo.",
      "Bata e faça dupla coagem na taça."
    ]
  },
  {
    "name": "Daiquiri",
    "nameItalic": "Daiquiri",
    "perfil": "Cítrico equilibrado",
    "copo": "Taça Cocktail",
    "foto": "https://images.unsplash.com/photo-1604908176997-125f25cc6f3d?q=80&w=400",
    "ingredientes": [
      { "qty": "50ml", "name": "Rum" },
      { "qty": "30ml", "name": "Suco de Limão" },
      { "qty": "15ml", "name": "Xarope de Açúcar" }
    ],
    "preparo": [
      "Adicione gelo na coqueteleira.",
      "Coloque todos os ingredientes.",
      "Bata e faça dupla coagem na taça."
    ]
  },
  {
    "name": "Moscow Mule",
    "nameItalic": "Mule",
    "perfil": "Refrescante picante",
    "copo": "Caneca de Cobre",
    "foto": "https://images.unsplash.com/photo-1513558161293-cdaf765ed2fd?q=80&w=400",
    "ingredientes": [
      { "qty": "50ml", "name": "Vodka" },
      { "qty": "25ml", "name": "Suco de Limão" },
      { "qty": "20ml", "name": "Xarope de Açúcar" },
      { "qty": "Top", "name": "Refrigerante de Gengibre" }
    ],
    "preparo": [
      "Adicione os ingredientes na coqueteleira com gelo.",
      "Bata e faça coagem simples.",
      "Sirva no copo com gelo e finalize com espuma."
    ]
  },
  {
    "name": "Affogato Alcoólico",
    "nameItalic": "Affogato",
    "perfil": "Doce intenso",
    "copo": "Taça Sobremesa",
    "foto": "https://images.unsplash.com/photo-1563805042-7684c019e1cb?q=80&w=400",
    "ingredientes": [
      { "qty": "40ml", "name": "Licor de Café" },
      { "qty": "40ml", "name": "Café" },
      { "qty": "1 bola", "name": "Sorvete de Creme" }
    ],
    "preparo": [
      "Adicione os ingredientes na taça.",
      "Misture levemente antes de servir."
    ]
  },
  {
    "name": "Caipirinha Tradicional",
    "nameItalic": "Caipi",
    "perfil": "Cítrico doce",
    "copo": "Copo Baixo",
    "foto": "https://images.unsplash.com/photo-1625944525533-473f1d3c79a3?q=80&w=400",
    "ingredientes": [
      { "qty": "75ml", "name": "Vodka ou Cachaça" },
      { "qty": "25ml", "name": "Xarope de Açúcar" },
      { "qty": "1 unidade", "name": "Limão Tahiti" }
    ],
    "preparo": [
      "Corte o limão e macere no copo.",
      "Adicione o xarope de açúcar.",
      "Complete com gelo e a bebida alcoólica.",
      "Misture bem."
    ]
  },
  {
    "name": "Caipirinha de Morango",
    "nameItalic": "Caipi Morango",
    "perfil": "Doce frutado",
    "copo": "Copo Baixo",
    "foto": "https://images.unsplash.com/photo-1598515214211-89d3c73ae83b?q=80&w=400",
    "ingredientes": [
      { "qty": "75ml", "name": "Vodka ou Cachaça" },
      { "qty": "25ml", "name": "Xarope de Açúcar" },
      { "qty": "5 unidades", "name": "Morangos" },
      { "qty": "25ml", "name": "Xarope de Morango" }
    ],
    "preparo": [
      "Macere os morangos no copo.",
      "Adicione o xarope de açúcar.",
      "Complete com gelo e álcool.",
      "Misture bem."
    ]
  },
  {
    "name": "Caipirinha de Bergamota",
    "nameItalic": "Caipi Bergamota",
    "perfil": "Cítrico suave",
    "copo": "Copo Baixo",
    "foto": "https://images.unsplash.com/photo-1551024601-bec78aea704b?q=80&w=400",
    "ingredientes": [
      { "qty": "75ml", "name": "Vodka ou Cachaça" },
      { "qty": "25ml", "name": "Xarope de Açúcar" },
      { "qty": "1/2 unidade", "name": "Limão" },
      { "qty": "4 gomos", "name": "Bergamota" }
    ],
    "preparo": [
      "Macere as frutas no copo.",
      "Adicione o xarope de açúcar.",
      "Complete com gelo e álcool.",
      "Misture bem."
    ]
  },
  {
    "name": "Saquê com Sabor",
    "nameItalic": "Saquê",
    "perfil": "Leve doce",
    "copo": "Copo Longo",
    "foto": "https://images.unsplash.com/photo-1617196035154-1e1f0f1ca5d4?q=80&w=400",
    "ingredientes": [
      { "qty": "75ml", "name": "Saquê" },
      { "qty": "25ml", "name": "Xarope de Sabor" },
      { "qty": "Top", "name": "Água Mineral" }
    ],
    "preparo": [
      "Adicione gelo ao copo.",
      "Coloque todos os ingredientes.",
      "Misture suavemente."
    ]
  },
  {
    "name": "Absprite",
    "nameItalic": "Absprite",
    "perfil": "Refrescante cítrico",
    "copo": "Copo Longo",
    "foto": "https://images.unsplash.com/photo-1582450871972-ab5ca641643d?q=80&w=400",
    "ingredientes": [
      { "qty": "50ml", "name": "Vodka" },
      { "qty": "10ml", "name": "Xarope de Açúcar" },
      { "qty": "10ml", "name": "Suco de Limão" },
      { "qty": "Top", "name": "Refrigerante de Limão" }
    ],
    "preparo": [
      "Monte o drink no copo com gelo.",
      "Adicione todos os ingredientes.",
      "Misture suavemente."
    ]
  },
  {
    "name": "Gaudério",
    "nameItalic": "Gaudério",
    "perfil": "Cítrico intenso",
    "copo": "Copo Baixo",
    "foto": "https://images.unsplash.com/photo-1605270012917-bf157c5a9541?q=80&w=400",
    "ingredientes": [
      { "qty": "40ml", "name": "Vodka" },
      { "qty": "40ml", "name": "Licor de Butiá" },
      { "qty": "40ml", "name": "Suco de Limão" },
      { "qty": "10ml", "name": "Xarope de Açúcar" }
    ],
    "preparo": [
      "Adicione todos os ingredientes na coqueteleira com gelo.",
      "Bata bem.",
      "Sirva em copo baixo com gelo."
    ]
  },
  {
    "name": "Red Fly",
    "nameItalic": "Red Fly",
    "perfil": "Doce amargo",
    "copo": "Taça Cocktail",
    "foto": "https://images.unsplash.com/photo-1544145945-f90425340c7e?q=80&w=400",
    "ingredientes": [
      { "qty": "50ml", "name": "Vodka" },
      { "qty": "20ml", "name": "Suco de Limão" },
      { "qty": "20ml", "name": "Xarope de Açúcar" },
      { "qty": "30ml", "name": "Campari ou Aperol" },
      { "qty": "1 unidade", "name": "Morango" },
      { "qty": "5 colheres chá", "name": "Albumina" }
    ],
    "preparo": [
      "Macere o morango com a vodka.",
      "Bata sem gelo e depois com gelo.",
      "Faça dupla coagem na taça."
    ]
  },
  {
    "name": "Sex on the Beach",
    "nameItalic": "Sex on the Beach",
    "perfil": "Doce frutado",
    "copo": "Copo Longo",
    "foto": "https://images.unsplash.com/photo-1582578598774-a377d4b322c6?q=80&w=400",
    "ingredientes": [
      { "qty": "40ml", "name": "Vodka" },
      { "qty": "25ml", "name": "Licor de Pêssego" },
      { "qty": "80ml", "name": "Suco de Laranja" },
      { "qty": "10ml", "name": "Xarope de Frutas Vermelhas" }
    ],
    "preparo": [
      "Bata o suco sem gelo.",
      "Monte o drink com gelo no copo.",
      "Finalize com o xarope."
    ]
  },
  {
    "name": "Cynar Fizz",
    "nameItalic": "Cynar Fizz",
    "perfil": "Amargo refrescante",
    "copo": "Copo Longo",
    "foto": "https://images.unsplash.com/photo-1598514983318-2f64f8f4796c?q=80&w=400",
    "ingredientes": [
      { "qty": "50ml", "name": "Cynar" },
      { "qty": "20ml", "name": "Cachaça" },
      { "qty": "25ml", "name": "Suco de Limão" },
      { "qty": "Top", "name": "Refrigerante de Limão" }
    ],
    "preparo": [
      "Adicione gelo ao copo.",
      "Coloque todos os ingredientes.",
      "Misture e complete com refrigerante."
    ]
  },
   {
    "name": "Mar Verde",
    "nameItalic": "Mar Verde",
    "perfil": "Cítrico herbal",
    "copo": "Copo Longo",
    "foto": "https://images.unsplash.com/photo-1551024601-bec78aea704b?q=80&w=400",
    "ingredientes": [
      { "qty": "60ml", "name": "Gin" },
      { "qty": "20ml", "name": "Curaçau Blue" },
      { "qty": "20ml", "name": "Xarope de Açúcar" },
      { "qty": "15ml", "name": "Cynar" },
      { "qty": "20ml", "name": "Suco de Limão" }
    ],
    "preparo": [
      "Adicione todos os ingredientes na coqueteleira com gelo.",
      "Bata bem.",
      "Faça dupla coagem em copo com gelo."
    ]
  },
  {
    "name": "MaraCuceva",
    "nameItalic": "MaraCuceva",
    "perfil": "Frutado leve",
    "copo": "Copo Longo",
    "foto": "https://images.unsplash.com/photo-1600271886742-f049cd451bba?q=80&w=400",
    "ingredientes": [
      { "qty": "40ml", "name": "Gin" },
      { "qty": "15ml", "name": "Xarope de Açúcar" },
      { "qty": "25ml", "name": "Suco de Maracujá" },
      { "qty": "Top", "name": "Cerveja" }
    ],
    "preparo": [
      "Bata os ingredientes na coqueteleira com gelo (exceto a cerveja).",
      "Faça dupla coagem em copo com gelo.",
      "Complete com cerveja."
    ]
  },
  {
    "name": "Whisky Sour",
    "nameItalic": "Whisky Sour",
    "perfil": "Ácido equilibrado",
    "copo": "Copo Baixo",
    "foto": "https://images.unsplash.com/photo-1587223962930-cb7f31384c19?q=80&w=400",
    "ingredientes": [
      { "qty": "60ml", "name": "Whisky" },
      { "qty": "25ml", "name": "Suco de Limão" },
      { "qty": "20ml", "name": "Xarope de Açúcar" },
      { "qty": "5 colheres chá", "name": "Albumina" }
    ],
    "preparo": [
      "Bata tudo com gelo na coqueteleira.",
      "Retire o gelo e bata novamente.",
      "Sirva em copo baixo e finalize com bitter."
    ]
  },
  {
    "name": "Kamikaze",
    "nameItalic": "Kamikaze",
    "perfil": "Cítrico forte",
    "copo": "Taça Cocktail",
    "foto": "https://images.unsplash.com/photo-1582450871972-ab5ca641643d?q=80&w=400",
    "ingredientes": [
      { "qty": "40ml", "name": "Vodka" },
      { "qty": "40ml", "name": "Licor de Laranja" },
      { "qty": "40ml", "name": "Suco de Limão" },
      { "qty": "10ml", "name": "Xarope de Açúcar" }
    ],
    "preparo": [
      "Bata todos os ingredientes com gelo.",
      "Faça dupla coagem em taça."
    ]
  },
  {
    "name": "Demonic",
    "nameItalic": "Demonic",
    "perfil": "Doce picante",
    "copo": "Taça Cocktail",
    "foto": "https://images.unsplash.com/photo-1544145945-f90425340c7e?q=80&w=400",
    "ingredientes": [
      { "qty": "50ml", "name": "Vodka" },
      { "qty": "40ml", "name": "Xarope de Morango" },
      { "qty": "30ml", "name": "Licor de Morango" },
      { "qty": "1 colher café", "name": "Pimenta Dedo de Moça" }
    ],
    "preparo": [
      "Bata tudo na coqueteleira com gelo.",
      "Faça dupla coagem na taça."
    ]
  },
  {
    "name": "Blue Lady",
    "nameItalic": "Blue Lady",
    "perfil": "Cítrico suave",
    "copo": "Taça Cocktail",
    "foto": "https://images.unsplash.com/photo-1582450871972-ab5ca641643d?q=80&w=400",
    "ingredientes": [
      { "qty": "50ml", "name": "Curaçau Blue" },
      { "qty": "30ml", "name": "Gin" },
      { "qty": "25ml", "name": "Suco de Limão" },
      { "qty": "5 colheres chá", "name": "Albumina" }
    ],
    "preparo": [
      "Bata com gelo e depois sem gelo.",
      "Faça dupla coagem na taça."
    ]
  },
  {
    "name": "Jasmine",
    "nameItalic": "Jasmine",
    "perfil": "Amargo cítrico",
    "copo": "Taça Cocktail",
    "foto": "https://images.unsplash.com/photo-1600271886742-f049cd451bba?q=80&w=400",
    "ingredientes": [
      { "qty": "45ml", "name": "Gin" },
      { "qty": "25ml", "name": "Suco de Limão" },
      { "qty": "10ml", "name": "Campari" },
      { "qty": "10ml", "name": "Licor de Laranja" }
    ],
    "preparo": [
      "Bata com gelo na coqueteleira.",
      "Faça dupla coagem em taça."
    ]
  },
  {
    "name": "Pink Lemonade",
    "nameItalic": "Pink Lemonade",
    "perfil": "Doce refrescante",
    "copo": "Copo Longo",
    "foto": "https://images.unsplash.com/photo-1551024601-bec78aea704b?q=80&w=400",
    "ingredientes": [
      { "qty": "10ml", "name": "Xarope de Morango" },
      { "qty": "15ml", "name": "Xarope de Açúcar" },
      { "qty": "25ml", "name": "Suco de Limão" },
      { "qty": "Top", "name": "Água com Gás" }
    ],
    "preparo": [
      "Monte o drink no copo com gelo.",
      "Misture e complete com água com gás."
    ]
  },
  {
    "name": "MaracuTequi",
    "nameItalic": "MaracuTequi",
    "perfil": "Frutado cítrico",
    "copo": "Copo Longo",
    "foto": "https://images.unsplash.com/photo-1600271886742-f049cd451bba?q=80&w=400",
    "ingredientes": [
      { "qty": "60ml", "name": "Tequila" },
      { "qty": "70ml", "name": "Maracujá" },
      { "qty": "30ml", "name": "Xarope de Açúcar" },
      { "qty": "60ml", "name": "Água com Gás" }
    ],
    "preparo": [
      "Bata os ingredientes na coqueteleira.",
      "Faça dupla coagem no copo com gelo.",
      "Complete com água com gás."
    ]
  },
  {
    "name": "Screwdriver",
    "nameItalic": "Screwdriver",
    "perfil": "Cítrico simples",
    "copo": "Copo Longo",
    "foto": "https://images.unsplash.com/photo-1577801598362-1f58f2c7f6b1?q=80&w=400",
    "ingredientes": [
      { "qty": "50ml", "name": "Vodka" },
      { "qty": "Top", "name": "Suco de Laranja" }
    ],
    "preparo": [
      "Monte no copo com gelo.",
      "Misture suavemente."
    ]
  },
  {
    "name": "Black Russian",
    "nameItalic": "Black Russian",
    "perfil": "Forte amargo",
    "copo": "Copo Baixo",
    "foto": "https://images.unsplash.com/photo-1604908554025-4b9c0fbd2d96?q=80&w=400",
    "ingredientes": [
      { "qty": "60ml", "name": "Vodka" },
      { "qty": "40ml", "name": "Licor de Café" }
    ],
    "preparo": [
      "Monte no copo com gelo.",
      "Mexa até gelar."
    ]
  },
  {
    "name": "Jambu Sour",
    "nameItalic": "Jambu Sour",
    "perfil": "Cítrico herbal",
    "copo": "Copo Baixo",
    "foto": "https://images.unsplash.com/photo-1587223962930-cb7f31384c19?q=80&w=400",
    "ingredientes": [
      { "qty": "60ml", "name": "Cachaça de Jambu" },
      { "qty": "25ml", "name": "Suco de Limão" },
      { "qty": "25ml", "name": "Xarope de Mel" },
      { "qty": "5 colheres chá", "name": "Albumina" }
    ],
    "preparo": [
      "Bata com gelo.",
      "Retire o gelo e bata novamente.",
      "Faça dupla coagem."
    ]
  },
  {
    "name": "Gin Tônica",
    "nameItalic": "Gin Tônica",
    "perfil": "Refrescante amargo",
    "copo": "Copo Longo",
    "foto": "https://images.unsplash.com/photo-1582450871972-ab5ca641643d?q=80&w=400",
    "ingredientes": [
      { "qty": "50ml", "name": "Gin" },
      { "qty": "30ml", "name": "Suco de Limão" },
      { "qty": "20ml", "name": "Xarope de Açúcar" },
      { "qty": "3 dashes", "name": "Bitter" }
    ],
    "preparo": [
      "Monte no copo com gelo.",
      "Misture suavemente."
    ]
  },
  {
    "name": "Batida Capeta",
    "nameItalic": "Capeta",
    "perfil": "Doce cremoso",
    "copo": "Copo Longo",
    "foto": "https://images.unsplash.com/photo-1572490122747-3968b75cc699?q=80&w=400",
    "ingredientes": [
      { "qty": "50ml", "name": "Destilado" },
      { "qty": "60g", "name": "Fruta" },
      { "qty": "45ml", "name": "Leite Condensado" },
      { "qty": "Gelo", "name": "A gosto" }
    ],
    "preparo": [
      "Bata tudo no liquidificador.",
      "Decore o copo e sirva."
    ]
  }
]

